dawn_sdk/__init__.py
dawn_sdk/auth.py
dawn_sdk/bucket.py
dawn_sdk/client.py
dawn_sdk/common.py
dawn_sdk/config.py
dawn_sdk/error.py
dawn_sdk/limited.py
dawn_sdk/mime.py
dawn_sdk/misc.py
dawn_sdk/portable.py
dawn_sdk/progress.py
dawn_sdk/result.py
dawn_sdk/test.py
dawn_sdk/url.py
dawn_sdk/xml_body.py
dawn_sdk-0.0.9.dist-info/METADATA
dawn_sdk-0.0.9.dist-info/RECORD
dawn_sdk-0.0.9.dist-info/WHEEL
dawn_sdk-0.0.9.dist-info/top_level.txt
